hasami/__init__.py
hasami/cli.py
hasami/hasami.py
hasami/util.py
hasami-0.0.1.dist-info/LICENSE
hasami-0.0.1.dist-info/METADATA
hasami-0.0.1.dist-info/WHEEL
hasami-0.0.1.dist-info/entry_points.txt
hasami-0.0.1.dist-info/top_level.txt
hasami-0.0.1.dist-info/RECORD
