Metadata-Version: 2.1
Name: hasami
Version: 0.0.1
Summary: Sentence segmentation for japanese text
Home-page: https://github.com/mkartawijaya/hasami
Author: Martin Kartawijaya
Author-email: pypi@m.kartawijaya.dev
License: BSD-3-Clause
Keywords: japanese,sentence,segmentation,nlp,sbd
Platform: UNKNOWN
Classifier: Development Status :: 3 - Alpha
Classifier: Programming Language :: Python :: 3
Classifier: Operating System :: OS Independent
Classifier: License :: OSI Approved :: BSD License
Classifier: Topic :: Text Processing :: Linguistic
Classifier: Natural Language :: Japanese
Requires-Python: >=3.6
